jiraextendedlib/__init__.py
jiraextendedlib/jira_extended.py
jiraextendedlib/jira_init.py
jiraextendedlib-0.4.2.7.dist-info/METADATA
jiraextendedlib-0.4.2.7.dist-info/WHEEL
jiraextendedlib-0.4.2.7.dist-info/top_level.txt
jiraextendedlib-0.4.2.7.dist-info/RECORD
