Metadata-Version: 2.4
Name: jiraextendedlib
Version: 0.4.2.7
Summary: An extended library for JIRA REST API interactions.
Author: Prasad Kodithuwakku
Requires-Dist: jira==3.2
